atk_training_nitesh_psq/__init__.py
atk_training_nitesh_psq/consumer/__init__.py
atk_training_nitesh_psq/manager/__init__.py
atk_training_nitesh_psq/producer/__init__.py
atk_training_nitesh_psq/sqlite_/__init__.py
atk_training_nitesh_psq-0.1.3.dist-info/WHEEL
atk_training_nitesh_psq-0.1.3.dist-info/entry_points.txt
atk_training_nitesh_psq-0.1.3.dist-info/METADATA
atk_training_nitesh_psq-0.1.3.dist-info/RECORD
