Metadata-Version: 2.1
Name: atk-training-nitesh-psq
Version: 0.1.3
Summary: 
Author: Nitesh
Author-email: nitesh@aganitha.ai
Requires-Python: >=3.10,<4.0
Classifier: Programming Language :: Python :: 3
Classifier: Programming Language :: Python :: 3.10
Classifier: Programming Language :: Python :: 3.11
Requires-Dist: PyYAML (>=6.0,<7.0)
Requires-Dist: db-sqlite3 (>=0.0.1,<0.0.2)
Requires-Dist: schedule (>=1.1.0,<2.0.0)
Requires-Dist: typer (>=0.7.0,<0.8.0)
